MANIFEST.in
README.md
setup.py
dynamicformset/__init__.py
dynamicformset/formset.py
dynamicformset/tests.py
dynamicformset.egg-info/PKG-INFO
dynamicformset.egg-info/SOURCES.txt
dynamicformset.egg-info/dependency_links.txt
dynamicformset.egg-info/requires.txt
dynamicformset.egg-info/top_level.txt
dynamicformset/static/dynamicformset/dynamicformset.css
dynamicformset/static/dynamicformset/dynamicformset.js
dynamicformset/templates/dynamicformset/base.html
dynamicformset/templates/dynamicformset/base_form.html