Metadata-Version: 1.0
Name: dynamicformset
Version: 0.2
Summary: UNKNOWN
Home-page: UNKNOWN
Author: Stan Misiurev
Author-email: misiurev@ncbi.nlm.nih.gov
License: BSD
Platform: UNKNOWN
